{
	"partitions" : [
		{
			"name" : "Top",
			"pins" : [
				{
					"name" : "send.data[0]",
					"strict" : false
				},
				{
					"name" : "send.data[1]",
					"strict" : false
				},
				{
					"name" : "send.data[2]",
					"strict" : false
				},
				{
					"name" : "send.data[3]",
					"strict" : false
				},
				{
					"name" : "send.data[4]",
					"strict" : false
				},
				{
					"name" : "send.data[5]",
					"strict" : false
				},
				{
					"name" : "send.data[6]",
					"strict" : false
				},
				{
					"name" : "send.data[7]",
					"strict" : false
				},
				{
					"name" : "send.data[8]",
					"strict" : false
				},
				{
					"name" : "send.data[9]",
					"strict" : false
				},
				{
					"name" : "send.data[10]",
					"strict" : false
				},
				{
					"name" : "send.data[11]",
					"strict" : false
				},
				{
					"name" : "clock",
					"strict" : false
				},
				{
					"name" : "recv.data[26]",
					"strict" : false
				},
				{
					"name" : "recv.data[28]",
					"strict" : false
				},
				{
					"name" : "recv.data[29]",
					"strict" : false
				},
				{
					"name" : "recv.data[30]",
					"strict" : false
				},
				{
					"name" : "recv.data[31]",
					"strict" : false
				},
				{
					"name" : "recv.data[27]",
					"strict" : false
				},
				{
					"name" : "recv.data[22]",
					"strict" : false
				},
				{
					"name" : "recv.data[23]",
					"strict" : false
				},
				{
					"name" : "recv.data[24]",
					"strict" : false
				},
				{
					"name" : "recv.data[25]",
					"strict" : false
				}
			]
		}
	]
}